MANIFEST.in
setup.py
webmsx/__init__.py
webmsx/snippet.py
webmsx/webmsx.py
webmsx/partials/code.inc.html
webmsx_mkdocs_plugin.egg-info/PKG-INFO
webmsx_mkdocs_plugin.egg-info/SOURCES.txt
webmsx_mkdocs_plugin.egg-info/dependency_links.txt
webmsx_mkdocs_plugin.egg-info/entry_points.txt
webmsx_mkdocs_plugin.egg-info/requires.txt
webmsx_mkdocs_plugin.egg-info/top_level.txt