Metadata-Version: 1.0
Name: webmsx-mkdocs-plugin
Version: 0.9.3
Summary: Embed WebMSX emulator in mkdocs documents.
Home-page: https://github.com/fmaida/webmsx-mkdocs-plugin
Author: Francesco Maida
Author-email: francesco.maida@gmail.com
License: MIT
Platform: UNKNOWN
